torchcriterion/__init__.py
torchcriterion-0.1.0.dist-info/licenses/LICENSE
torchcriterion-0.1.0.dist-info/METADATA
torchcriterion-0.1.0.dist-info/WHEEL
torchcriterion-0.1.0.dist-info/top_level.txt
torchcriterion-0.1.0.dist-info/RECORD
