Metadata-Version: 2.4
Name: torchcriterion
Version: 0.1.0
Summary: A modular PyTorch loss function library with popular criteria for classification, regression, segmentation, and metric learning.
Author: TransformerTitan
Author-email: Your Name <you@example.com>
License: MIT
Keywords: pytorch,loss,criterion,deep learning,machine learning
Classifier: Programming Language :: Python :: 3
Classifier: License :: OSI Approved :: MIT License
Classifier: Operating System :: OS Independent
Requires-Python: >=3.7
License-File: LICENSE
Requires-Dist: torch>=2.0
Dynamic: author
Dynamic: license-file
Dynamic: requires-python
